pygeostandards/__init__.py
pygeostandards/basecollection.py
pygeostandards/baseitem.py
pygeostandards/continents.py
pygeostandards/countries.py
pygeostandards/currencies.py
pygeostandards/euronuts.py
pygeostandards/euroregions.py
pygeostandards/historiccountries.py
pygeostandards/info.py
pygeostandards/languages.py
pygeostandards/regions.py
pygeostandards/scripts.py
pygeostandards/subdivisions.py
pygeostandards/utils.py
pygeostandards-0.2.1.dist-info/METADATA
pygeostandards-0.2.1.dist-info/RECORD
pygeostandards-0.2.1.dist-info/WHEEL
pygeostandards-0.2.1.dist-info/top_level.txt
