Metadata-Version: 2.1
Name: pygeostandards
Version: 0.2.1
Summary: A small package to take care of geographic and other standard information.
Home-page: https://github.com/mattange/pygeostandards
Author: Matteo Angeloni
Author-email: mattange@gmail.com
License: UNKNOWN
Project-URL: Source, https://github.com/mattange/pygeostandards
Project-URL: Bug Reports, https://github.com/mattange/pygeostandards/issues
Keywords: ISO country geography NUTS currencies languages regions scripts
Platform: UNKNOWN
Classifier: Development Status :: 4 - Beta
Classifier: Intended Audience :: Developers
Classifier: Programming Language :: Python :: 3
Classifier: License :: OSI Approved :: MIT License
Classifier: Operating System :: OS Independent
Classifier: Natural Language :: English
Classifier: Topic :: Software Development :: Libraries
Requires-Python: >=3.5
